{
  "updated": "2026-07-11",
  "summary": "",
  "headlines": [
    {
      "ticker": "^GSPC",
      "company": "経済",
      "title": "Stock Market Today, July 10: Markets Edge Higher and SK Hynix Soars on Debut",
      "publisher": "Motley Fool",
      "link": "https://www.fool.com/coverage/stock-market-today/2026/07/10/stock-market-today-july-10-markets-edge-higher-and-sk-hynix-soars-on-debut/",
      "time": "2026-07-10T21:25:05Z",
      "titleJa": "今日、7月10日の株式市場: 市場はじり高、SKハイニックスはデビューで急騰"
    },
    {
      "ticker": "^DJI",
      "company": "経済",
      "title": "U.S. Stock Market Ticks Higher With Memory Chip Maker’s Big Debut",
      "publisher": "The Wall Street Journal",
      "link": "https://www.wsj.com/finance/stocks/u-s-stock-market-ticks-higher-with-memory-chip-makers-big-debut-e3193b33?siteid=yhoof2&yptr=yahoo",
      "time": "2026-07-10T21:20:00Z",
      "titleJa": "メモリチップメーカーの大々的なデビューで米国株式市場が上昇"
    },
    {
      "ticker": "^GSPC",
      "company": "経済",
      "title": "Subversive Capital files 'Ex-Elon' ETFs with the SEC that strip Tesla and SpaceX from the S&P 500 and Nasdaq-100",
      "publisher": "Moneywise",
      "link": "https://finance.yahoo.com/markets/stocks/articles/subversive-capital-files-ex-elon-211500636.html",
      "time": "2026-07-10T21:15:00Z",
      "titleJa": "Subversive Capital、テスラとスペースXをS&P 500とナスダック100から剥奪する「Ex-Elon」ETFをSECに申請"
    },
    {
      "ticker": "^GSPC",
      "company": "経済",
      "title": "This Stock Market Is Full of Bargains, Our Roundtable Pros Say. 45 Picks for the Second Half.",
      "publisher": "Barrons.com",
      "link": "https://www.barrons.com/articles/barrons-roundtable-stock-picks-top-investors-ab1990a9?siteid=yhoof2&yptr=yahoo",
      "time": "2026-07-10T21:13:00Z",
      "titleJa": "この株式市場はお買い得品に満ちている、とラウンドテーブルのプロは言います。後半の45ピック。"
    },
    {
      "ticker": "^GSPC",
      "company": "経済",
      "title": "How Hewlett Packard Built A Fortress Out Of Its Backlog",
      "publisher": "Trefis",
      "link": "https://www.trefis.com/articles/606606/how-hewlett-packard-built-a-fortress-out-of-its-backlog/2026-07-10",
      "time": "2026-07-10T21:12:27Z",
      "titleJa": "ヒューレット・パッカードはどのようにして受注残から要塞を構築したか"
    },
    {
      "ticker": "^IXIC",
      "company": "経済",
      "title": "Stocks to Watch Recap: SK Hynix, EasyJet, Circle, Vodafone",
      "publisher": "The Wall Street Journal",
      "link": "https://www.wsj.com/livecoverage/stock-market-today-dow-sp-500-nasdaq-07-10-2026/card/stocks-to-watch-sk-hynix-easyjet-vodafone-9jRubZCK4RwBfuX2M50M?siteid=yhoof2&yptr=yahoo",
      "time": "2026-07-10T21:07:54Z",
      "titleJa": "注目銘柄の要約: SK Hynix、EasyJet、Circle、Vodafone"
    }
  ]
}