{
  "updated": "2026-06-05",
  "summary": "",
  "headlines": [
    {
      "ticker": "^GSPC",
      "company": "経済",
      "title": "Morgan Stanley makes bold new call on Micron stock",
      "publisher": "TheStreet",
      "link": "https://www.thestreet.com/investing/stocks/morgan-stanley-raises-price-target-on-micron-stock",
      "time": "2026-06-04T22:07:00Z",
      "titleJa": "モルガン・スタンレーがマイクロン株に対して大胆な新たな要求を行う"
    },
    {
      "ticker": "^GSPC",
      "company": "経済",
      "title": "Dow Jones Hits High, AI Stocks Shrug Off Broadcom, Ciena Sell-Offs; Jobs Report Looms",
      "publisher": "Investor's Business Daily",
      "link": "https://www.investors.com/market-trend/stock-market-today/dow-jones-futures-ai-stocks-broadcom-ciena-jobs-report/?src=A00220&yptr=yahoo",
      "time": "2026-06-04T22:04:20Z",
      "titleJa": "ダウ・ジョーンズは高値を記録、AI株はブロードコムを無視、シエナの下落。ジョブレポートルーム"
    },
    {
      "ticker": "^GSPC",
      "company": "経済",
      "title": "Stock Market Today, June 4: Nu Holdings Jumps After Board Approves $1 Billion Share Buyback",
      "publisher": "Motley Fool",
      "link": "https://www.fool.com/coverage/stock-market-today/2026/06/04/stock-market-today-june-4-nu-holdings-jumps-after-board-approves-usd1-billion-share-buyback/",
      "time": "2026-06-04T21:51:55Z",
      "titleJa": "今日の株式市場、6月4日: 取締役会が10億ドルの自社株買いを承認した後、Nu Holdingsが急騰"
    },
    {
      "ticker": "^GSPC",
      "company": "経済",
      "title": "3 Consumer Stocks with Warning Signs",
      "publisher": "StockStory",
      "link": "https://finance.yahoo.com/markets/stocks/articles/3-consumer-stocks-warning-signs-214930600.html",
      "time": "2026-06-04T21:49:30Z",
      "titleJa": "3 警告サインのある消費者株"
    },
    {
      "ticker": "^IXIC",
      "company": "経済",
      "title": "Stock Market Today, June 4: Bank of America Rises as Cross-Border Payments Plan Expands Transaction Banking",
      "publisher": "Motley Fool",
      "link": "https://www.fool.com/coverage/stock-market-today/2026/06/04/stock-market-today-june-4-bank-of-america-rises-as-cross-border-payments-plan-expands-transaction-banking/",
      "time": "2026-06-04T21:37:20Z",
      "titleJa": "今日の株式市場、6月4日: 国境を越えた決済計画によりトランザクションバンキングが拡大され、バンク・オブ・アメリカが上昇"
    },
    {
      "ticker": "^DJI",
      "company": "経済",
      "title": "Oil drops, stocks mostly higher despite AI concerns",
      "publisher": "AFP",
      "link": "https://finance.yahoo.com/markets/stocks/articles/stocks-drop-ai-rate-hike-030621040.html",
      "time": "2026-06-04T21:36:56Z",
      "titleJa": "AI懸念にもかかわらず、原油は下落、株価はほぼ上昇"
    }
  ]
}